tolvera/__init__.py
tolvera/__main__.py
tolvera/context.py
tolvera/cv.py
tolvera/dualsense.py
tolvera/iml.py
tolvera/mp/__init__.py
tolvera/mp/face.py
tolvera/mp/face_mesh.py
tolvera/mp/face_mesh_connections.py
tolvera/mp/hands.py
tolvera/mp/pose.py
tolvera/npndarray_dict.py
tolvera/osc/__init__.py
tolvera/osc/maxmsp.py
tolvera/osc/osc.py
tolvera/osc/oscmap.py
tolvera/osc/pd.py
tolvera/osc/update.py
tolvera/particles.py
tolvera/patches.py
tolvera/pixels.py
tolvera/rec.py
tolvera/sketchbook.py
tolvera/species.py
tolvera/state.py
tolvera/taichi_.py
tolvera/tolvera_.py
tolvera/utils.py
tolvera/vera/__init__.py
tolvera/vera/flock.py
tolvera/vera/forces.py
tolvera/vera/gol.py
tolvera/vera/particle_life.py
tolvera/vera/reaction_diffusion.py
tolvera/vera/slime.py
tolvera/vera/swarmalators.py
tolvera-0.1.0rc15.post1.dist-info/LICENSE
tolvera-0.1.0rc15.post1.dist-info/METADATA
tolvera-0.1.0rc15.post1.dist-info/WHEEL
tolvera-0.1.0rc15.post1.dist-info/RECORD
