Metadata-Version: 2.3
Name: tolvera
Version: 0.1.0rc15.post1
Summary: Tölvera is a library for exploring music interaction with artificial life and self-organising systems.
License: AGPL-3.0
Author: Jack Armitage
Author-email: jack.armitage@me.com
Requires-Python: >=3.10,<3.13
Classifier: License :: OSI Approved :: GNU Affero General Public License v3
Classifier: Programming Language :: Python :: 3
Classifier: Programming Language :: Python :: 3.10
Classifier: Programming Language :: Python :: 3.11
Classifier: Programming Language :: Python :: 3.12
Requires-Dist: anguilla-iml (==0.3.0)
Requires-Dist: dualsense-controller (>=0.2.0,<0.3.0)
Requires-Dist: iipyper (>=0.1.0b1,<0.2.0)
Requires-Dist: jsons (>=1.6.3,<2.0.0)
Requires-Dist: mediapipe (==0.10.20)
Requires-Dist: opencv-python (>=4.8.1.78,<5.0.0.0)
Requires-Dist: sardine (>=0.0.0b3,<0.0.1)
Requires-Dist: taichi (>=1.7.0,<2.0.0)
Requires-Dist: torch (>=2.2.2,<3.0.0)
Requires-Dist: tqdm (>=4.66.4,<5.0.0)
Project-URL: Documentation, https://intelligent-instruments-lab.github.io/tolvera/
Project-URL: Repository, https://github.com/Intelligent-Instruments-Lab/tolvera
